{"sectors":[[[{"id":"1c83c71f-f051-40ba-b591-183e040addd6","position":{"x":0,"y":0},"teamId":"34214631246321463123","type":"Capital","namespace":"buildings"}],[],[],[{"id":"58eb376a-ed8b-4084-be05-0c4c646e23c3","position":{"x":0,"y":3},"teamId":"neutral","type":"Mountain","namespace":"obstacles"}],[],[],[],[]],[[],[],[],[{"id":"eda37701-ab8c-4ffc-8365-4952db04768b","position":{"x":1,"y":3},"teamId":"neutral","type":"Mountain","namespace":"obstacles"}],[],[],[],[]],[[],[],[],[{"id":"eb19e8af-97c9-447c-8c20-ad44c578c254","position":{"x":2,"y":3},"teamId":"neutral","type":"Mountain","namespace":"obstacles"}],[],[],[],[]],[[],[],[],[{"id":"9f5979f8-b27f-41dd-b2fe-4e4ea20bdf3b","position":{"x":3,"y":3},"teamId":"neutral","type":"Mountain","namespace":"obstacles"}],[],[],[],[]],[[],[],[],[{"id":"b84c0038-cfd5-4f89-80b7-cf8135cc9a2b","position":{"x":4,"y":3},"teamId":"neutral","type":"Mountain","namespace":"obstacles"}],[],[],[],[]],[[],[],[],[{"id":"af948946-2b96-4aca-91a9-867388fe1164","position":{"x":5,"y":3},"teamId":"neutral","type":"Mountain","namespace":"obstacles"}],[],[],[],[]],[[],[],[],[{"id":"1d2ce34c-a969-41e1-a284-d9b6b439a598","position":{"x":6,"y":3},"teamId":"neutral","type":"Mountain","namespace":"obstacles"}],[],[],[],[]],[[],[],[],[],[],[],[],[{"id":"9b7ac6e1-0b0a-407e-9bb5-42ebf3773fcf","position":{"x":7,"y":7},"teamId":"91463216425320541230","type":"Capital","namespace":"buildings"}]]],"entities":{"1c83c71f-f051-40ba-b591-183e040addd6":{"id":"1c83c71f-f051-40ba-b591-183e040addd6","position":{"x":0,"y":0},"teamId":"34214631246321463123","type":"Capital","namespace":"buildings"},"9b7ac6e1-0b0a-407e-9bb5-42ebf3773fcf":{"id":"9b7ac6e1-0b0a-407e-9bb5-42ebf3773fcf","position":{"x":7,"y":7},"teamId":"91463216425320541230","type":"Capital","namespace":"buildings"},"58eb376a-ed8b-4084-be05-0c4c646e23c3":{"id":"58eb376a-ed8b-4084-be05-0c4c646e23c3","position":{"x":0,"y":3},"teamId":"neutral","type":"Mountain","namespace":"obstacles"},"eda37701-ab8c-4ffc-8365-4952db04768b":{"id":"eda37701-ab8c-4ffc-8365-4952db04768b","position":{"x":1,"y":3},"teamId":"neutral","type":"Mountain","namespace":"obstacles"},"eb19e8af-97c9-447c-8c20-ad44c578c254":{"id":"eb19e8af-97c9-447c-8c20-ad44c578c254","position":{"x":2,"y":3},"teamId":"neutral","type":"Mountain","namespace":"obstacles"},"9f5979f8-b27f-41dd-b2fe-4e4ea20bdf3b":{"id":"9f5979f8-b27f-41dd-b2fe-4e4ea20bdf3b","position":{"x":3,"y":3},"teamId":"neutral","type":"Mountain","namespace":"obstacles"},"b84c0038-cfd5-4f89-80b7-cf8135cc9a2b":{"id":"b84c0038-cfd5-4f89-80b7-cf8135cc9a2b","position":{"x":4,"y":3},"teamId":"neutral","type":"Mountain","namespace":"obstacles"},"af948946-2b96-4aca-91a9-867388fe1164":{"id":"af948946-2b96-4aca-91a9-867388fe1164","position":{"x":5,"y":3},"teamId":"neutral","type":"Mountain","namespace":"obstacles"},"1d2ce34c-a969-41e1-a284-d9b6b439a598":{"id":"1d2ce34c-a969-41e1-a284-d9b6b439a598","position":{"x":6,"y":3},"teamId":"neutral","type":"Mountain","namespace":"obstacles"}},"influence":[["neutral","neutral","neutral","neutral","neutral","neutral","neutral","neutral"],["neutral","neutral","neutral","neutral","neutral","neutral","neutral","neutral"],["neutral","neutral","neutral","neutral","neutral","neutral","neutral","neutral"],["neutral","neutral","neutral","neutral","neutral","neutral","neutral","neutral"],["neutral","neutral","neutral","neutral","neutral","neutral","neutral","neutral"],["neutral","neutral","neutral","neutral","neutral","neutral","neutral","neutral"],["neutral","neutral","neutral","neutral","neutral","neutral","neutral","neutral"],["neutral","neutral","neutral","neutral","neutral","neutral","neutral","neutral"]]}